jugendschutzprogramm/__init__.py
jugendschutzprogramm/api.py
jugendschutzprogramm-0.1.2.dist-info/METADATA
jugendschutzprogramm-0.1.2.dist-info/WHEEL
jugendschutzprogramm-0.1.2.dist-info/RECORD
