Metadata-Version: 2.1
Name: jugendschutzprogramm
Version: 0.1.2
Summary: An API Client to query the API of the one and only officially approved sfilter solution in Germany to protect minors from harmful content on the internet.
License: Apache 2.0
Author: Lilith Wittmann
Author-email: mail@lilithwittmann.de
Requires-Python: >=3.9
Classifier: License :: Other/Proprietary License
Classifier: Programming Language :: Python :: 3
Classifier: Programming Language :: Python :: 3.9
Classifier: Programming Language :: Python :: 3.10
Classifier: Programming Language :: Python :: 3.11
Classifier: Programming Language :: Python :: 3.12
Requires-Dist: requests (>=2.31.0,<3.0.0)
